{"product":{"response":"INVISIBLE","searchableProductInfo":{"details":"Multicolored animal-print silkOptional chain shoulder strap, gunmetal frame, ruched, fully lined in signature red twillInternal pouch pocketSignature shoe clasp fastening at top","productNavigationCategories":[{"category":"Bags","productType":"Clutch_Bags","productSubType":"Clutch_Bags"}],"designer":"Christian Louboutin","productId":178084,"title":"Mini Loubi Lula animal-print silk frame clutch","editorsNotes":"Christian Louboutin's animal-print silk clutch will instantly elevate your party outfit. Carry it with a floor-skimming color-block gown to ensure the playful print stands out.Shown here with: 3.1 Phillip Lim gown, Kenneth Jay Lane cuff, Jimmy Choo boots.","price":"&pound;272","eventId":null,"colour":"Animal_Print","discountPercentage":0.5,"originalPrice":"&pound;545","last_update_dts":"2012-12-10","sizes":[{"size":"One Size","usSize":null,"sku":"178084-005","onOrder":false,"displaySize":"One Size","stockLevel":"OUT_OF_STOCK"}],"imageUrls":["http://cache.net-a-porter.com/images/products/178084/178084_in_m.jpg","http://cache.net-a-porter.com/images/products/178084/178084_ou_m.jpg","http://cache.net-a-porter.com/images/products/178084/178084_fr_m.jpg","http://cache.net-a-porter.com/images/products/178084/178084_bk_m.jpg","http://cache.net-a-porter.com/images/products/178084/178084_cu_m.jpg","http://cache.net-a-porter.com/images/products/178084/178084_e1_m.jpg","http://cache.net-a-porter.com/images/products/178084/178084_e2_m.jpg"],"sizeAndFit":"<ul><li> Weighs approximately 0.9lbs/ 0.4kg<li> Width 9\" / 24cm<li> Height 6\" / 16cm<li> Depth 2\" / 6cm<li> Handle Drop 9\" / 24cm<li> Min. Strap Length 20\" / 52cm<li> Max. Strap Length 20\" / 52cm</ul>","discountPercentageAsNonFraction":50,"discounted":true,"otherColours":[]}},"immersive":{"designer":"Christian Louboutin","productId":178084,"title":"Mini Loubi Lula animal-print silk frame clutch","price":"&pound;272","searchCriteriaMap":{"product_id":["178084"]},"images":[{"thumb":"http://cache.net-a-porter.com/images/products/178084/178084_in_m.jpg","fullSize":"http://cache.net-a-porter.com/images/products/178084/178084_in_xl.jpg"},{"thumb":"http://cache.net-a-porter.com/images/products/178084/178084_ou_m.jpg","fullSize":"http://cache.net-a-porter.com/images/products/178084/178084_ou_xl.jpg"},{"thumb":"http://cache.net-a-porter.com/images/products/178084/178084_fr_m.jpg","fullSize":"http://cache.net-a-porter.com/images/products/178084/178084_fr_xl.jpg"},{"thumb":"http://cache.net-a-porter.com/images/products/178084/178084_bk_m.jpg","fullSize":"http://cache.net-a-porter.com/images/products/178084/178084_bk_xl.jpg"},{"thumb":"http://cache.net-a-porter.com/images/products/178084/178084_cu_m.jpg","fullSize":"http://cache.net-a-porter.com/images/products/178084/178084_cu_xl.jpg"},{"thumb":"http://cache.net-a-porter.com/images/products/178084/178084_e1_m.jpg","fullSize":"http://cache.net-a-porter.com/images/products/178084/178084_e1_xl.jpg"},{"thumb":"http://cache.net-a-porter.com/images/products/178084/178084_e2_m.jpg","fullSize":"http://cache.net-a-porter.com/images/products/178084/178084_e2_xl.jpg"}],"pageTitle":"Get The Look"}}